linkedindb
