Metadata-Version: 2.1
Name: linkedindb
Version: 0.0.3
Summary: LinkedIn Driver.
Home-page: https://gitlab.com/wefindx/linkedin
Author: Mindey
Author-email: mindey@qq.com
License: ASK FOR PERMISSIONS
Platform: UNKNOWN
Provides-Extra: test
